deepquantiles/__init__.py
deepquantiles/datasets.py
deepquantiles/nb_utils.py
deepquantiles/presets.py
deepquantiles/regressors/__init__.py
deepquantiles/regressors/batches.py
deepquantiles/regressors/cdf.py
deepquantiles/regressors/losses.py
deepquantiles/regressors/mdn.py
deepquantiles/regressors/multiquantile.py
deepquantiles-0.0.2.dist-info/LICENSE
deepquantiles-0.0.2.dist-info/METADATA
deepquantiles-0.0.2.dist-info/WHEEL
deepquantiles-0.0.2.dist-info/entry_points.txt
deepquantiles-0.0.2.dist-info/top_level.txt
deepquantiles-0.0.2.dist-info/RECORD
