Metadata-Version: 2.1
Name: deepquantiles
Version: 0.0.2
Summary: Deep Continuous Quantile Regression
Home-page: https://github.com/ig248/deepquantiles
Author: Igor Gotlibovych
Author-email: igor.gotlibovych@gmail.com
License: MIT
Platform: UNKNOWN
Classifier: Intended Audience :: Developers
Classifier: Operating System :: OS Independent
Classifier: Programming Language :: Python
Classifier: Programming Language :: Python :: 3
Classifier: Programming Language :: Python :: 3.6
Requires-Dist: keras
Requires-Dist: scikit-learn
